twitch_dl-3.3.1.dist-info/licenses/LICENSE
twitchdl/__init__.py
twitchdl/__main__.py
twitchdl/cache.py
twitchdl/cli.py
twitchdl/entities.py
twitchdl/exceptions.py
twitchdl/fonts.py
twitchdl/http.py
twitchdl/naming.py
twitchdl/output.py
twitchdl/playlists.py
twitchdl/progress.py
twitchdl/subonly.py
twitchdl/twitch.py
twitchdl/twitch_async.py
twitchdl/utils.py
twitchdl/chat/__init__.py
twitchdl/chat/json.py
twitchdl/chat/utils.py
twitchdl/chat/video.py
twitchdl/chat/ytt.py
twitchdl/commands/__init__.py
twitchdl/commands/clips.py
twitchdl/commands/download.py
twitchdl/commands/info.py
twitchdl/commands/videos.py
twitch_dl-3.3.1.dist-info/METADATA
twitch_dl-3.3.1.dist-info/WHEEL
twitch_dl-3.3.1.dist-info/entry_points.txt
twitch_dl-3.3.1.dist-info/top_level.txt
twitch_dl-3.3.1.dist-info/RECORD
