Metadata-Version: 2.4
Name: twitch-dl
Version: 3.3.1
Summary: Quickly download videos from twitch.tv from the comort of your terminal emulator
Author-email: Ivan Habunek <ivan@habunek.com>
License:                     GNU GENERAL PUBLIC LICENSE
Project-URL: Homepage, https://twitch-dl.bezdomni.net/
Project-URL: Source, https://github.com/ihabunek/twitch-dl
Keywords: twitch,vod,video,download
Classifier: Development Status :: 5 - Production/Stable
Classifier: Environment :: Console
Classifier: License :: OSI Approved :: GNU General Public License v3 (GPLv3)
Classifier: Operating System :: OS Independent
Requires-Python: >=3.9
License-File: LICENSE
Requires-Dist: click<9.0.0,>=8.0.0
Requires-Dist: httpx<1.0.0,>=0.17.0
Requires-Dist: m3u8<7.0.0,>=3.0.0
Requires-Dist: wcwidth<1.0.0,>=0.2
Provides-Extra: chat
Requires-Dist: pillow>=9; extra == "chat"
Requires-Dist: fonttools<5,>=4; extra == "chat"
Dynamic: license-file
